nerv/__init__.py
nerv/app.py
nerv/utility.py
nerv-1.0.0.dist-info/LICENSE
nerv-1.0.0.dist-info/METADATA
nerv-1.0.0.dist-info/WHEEL
nerv-1.0.0.dist-info/top_level.txt
nerv-1.0.0.dist-info/RECORD
