Metadata-Version: 2.1
Name: nerv
Version: 1.0.0
Summary: Neuroimaging Results Visualization
Home-page: https://github.com/rmanaem/nerv
Author: (rmanaem) Arman Jahanpour
Author-email: <armanjahanpour7@gmail.com>
License: MIT
Keywords: python,dash,pandas,data visualization
Platform: UNKNOWN
Classifier: Development Status :: 5 - Production/Stable
Classifier: Intended Audience :: Developers
Classifier: Programming Language :: Python :: 3
Classifier: Operating System :: Unix
Classifier: Operating System :: MacOS :: MacOS X
Classifier: Operating System :: Microsoft :: Windows
License-File: LICENSE
Requires-Dist: Brotli (==1.0.9)
Requires-Dist: click (==8.0.4)
Requires-Dist: colorama (==0.4.4)
Requires-Dist: dash (==2.3.0)
Requires-Dist: dash-bootstrap-components (==1.0.3)
Requires-Dist: dash-bootstrap-templates (==1.0.5)
Requires-Dist: dash-core-components (==2.0.0)
Requires-Dist: dash-html-components (==2.0.0)
Requires-Dist: dash-table (==5.0.0)
Requires-Dist: Flask (==2.0.3)
Requires-Dist: Flask-Compress (==1.11)
Requires-Dist: itsdangerous (==2.1.1)
Requires-Dist: Jinja2 (==3.0.3)
Requires-Dist: MarkupSafe (==2.1.1)
Requires-Dist: numpy (==1.22.3)
Requires-Dist: pandas (==1.4.1)
Requires-Dist: plotly (==5.6.0)
Requires-Dist: python-dateutil (==2.8.2)
Requires-Dist: pytz (==2022.1)
Requires-Dist: six (==1.16.0)
Requires-Dist: tenacity (==8.0.1)
Requires-Dist: Werkzeug (==2.0.3)
